aioxiaomi/__init__.py
aioxiaomi/__main__.py
aioxiaomi/aioxiaomi.py
aioxiaomi/discover.py
aioxiaomi-0.1.5.dist-info/LICENSE.txt
aioxiaomi-0.1.5.dist-info/METADATA
aioxiaomi-0.1.5.dist-info/WHEEL
aioxiaomi-0.1.5.dist-info/entry_points.txt
aioxiaomi-0.1.5.dist-info/top_level.txt
aioxiaomi-0.1.5.dist-info/RECORD
