Metadata-Version: 2.1
Name: aioxiaomi
Version: 0.1.5
Summary: API for local communication with Xiaomi devices over a LAN with asyncio.
Home-page: http://github.com/frawau/aioxiaomi
Author: François Wautier
Author-email: francois@wautier.eu
License: MIT
Keywords: yeelight,light,automation,xiaomi
Platform: UNKNOWN
Classifier: License :: OSI Approved :: MIT License
Classifier: Programming Language :: Python :: 3
Classifier: Programming Language :: Python :: 3.5
